tutompy/__init__.py
tutompy/console.py
tutompy/wikipedia.py
tutompy-1.0.0.dist-info/entry_points.txt
tutompy-1.0.0.dist-info/LICENSE
tutompy-1.0.0.dist-info/WHEEL
tutompy-1.0.0.dist-info/METADATA
tutompy-1.0.0.dist-info/RECORD
