Metadata-Version: 2.1
Name: tutompy
Version: 1.0.0
Summary: The hypermodern Python project
Home-page: https://github.com/pamlinux/tutompy
License: MIT
Keywords: hypermodern
Author: Pierre-Alain Moret
Author-email: moret.pierre.alain@gmail.com
Requires-Python: >=3.8,<4.0
Classifier: License :: OSI Approved :: MIT License
Classifier: Programming Language :: Python :: 3
Classifier: Programming Language :: Python :: 3.8
Requires-Dist: click (>=7.1.2,<8.0.0)
Requires-Dist: desert (>=2020.11.18,<2021.0.0)
Requires-Dist: marshmallow (>=3.11.1,<4.0.0)
Requires-Dist: requests (>=2.25.1,<3.0.0)
Project-URL: Repository, https://github.com/pamlinux/tutompy
